zny_yespower_0_5.cp36-win32.pyd
zny_yespower_0_5-1.0.2.dist-info/METADATA
zny_yespower_0_5-1.0.2.dist-info/WHEEL
zny_yespower_0_5-1.0.2.dist-info/top_level.txt
zny_yespower_0_5-1.0.2.dist-info/RECORD
