Metadata-Version: 2.1
Name: zny-yespower-0-5
Version: 1.0.2
Summary: Bindings for yespower-0.5 proof of work used by bitzeny
Home-page: https://github.com/bitzeny-electrum/zny_yespower_0_5_python3
Author: y-chan
Author-email: yuto_tetuota@yahoo.co.jp
License: UNKNOWN
Platform: UNKNOWN
